learnlock/__init__.py
learnlock/cli.py
learnlock/config.py
learnlock/duel.py
learnlock/hud.py
learnlock/llm.py
learnlock/ocr.py
learnlock/scheduler.py
learnlock/storage.py
learnlock/tools/__init__.py
learnlock/tools/article.py
learnlock/tools/github.py
learnlock/tools/pdf.py
learnlock/tools/youtube.py
learnlock-0.1.5.dist-info/METADATA
learnlock-0.1.5.dist-info/WHEEL
learnlock-0.1.5.dist-info/entry_points.txt
learnlock-0.1.5.dist-info/licenses/LICENSE
learnlock-0.1.5.dist-info/RECORD
