Metadata-Version: 2.4
Name: learnlock
Version: 0.1.5
Summary: The app that argues with you. Adversarial Socratic learning with spaced repetition.
Project-URL: Homepage, https://github.com/MitudruDutta/learnlock
Project-URL: Repository, https://github.com/MitudruDutta/learnlock
Project-URL: Issues, https://github.com/MitudruDutta/learnlock/issues
Author-email: Mitudru Dutta <mitudrudutta72@gmail.com>
License: MIT
License-File: LICENSE
Keywords: ai,cli,education,flashcards,learning,socratic,spaced-repetition
Classifier: Development Status :: 4 - Beta
Classifier: Environment :: Console
Classifier: Intended Audience :: Developers
Classifier: Intended Audience :: Education
Classifier: License :: OSI Approved :: MIT License
Classifier: Operating System :: OS Independent
Classifier: Programming Language :: Python :: 3
Classifier: Programming Language :: Python :: 3.11
Classifier: Programming Language :: Python :: 3.12
Classifier: Programming Language :: Python :: 3.13
Classifier: Topic :: Education
Requires-Python: >=3.11
Requires-Dist: google-generativeai>=0.3.0
Requires-Dist: groq>=0.4.0
Requires-Dist: litellm>=1.0.0
Requires-Dist: pillow>=10.0.0
Requires-Dist: pymupdf>=1.23.0
Requires-Dist: python-dotenv>=1.0.0
Requires-Dist: requests>=2.28.0
Requires-Dist: rich>=13.0.0
Requires-Dist: trafilatura>=1.6.0
Requires-Dist: typer>=0.9.0
Requires-Dist: youtube-transcript-api>=0.6.0
Requires-Dist: yt-dlp>=2023.0.0
Provides-Extra: dev
Requires-Dist: build; extra == 'dev'
Requires-Dist: pytest; extra == 'dev'
Requires-Dist: ruff; extra == 'dev'
Requires-Dist: twine; extra == 'dev'
Provides-Extra: ocr
Requires-Dist: easyocr; extra == 'ocr'
Requires-Dist: pillow; extra == 'ocr'
Provides-Extra: whisper
Requires-Dist: groq; extra == 'whisper'
Requires-Dist: yt-dlp; extra == 'whisper'
